setup.py
myautoresizer/__init__.py
myautoresizer/my-autoresizer.ini
myautoresizer/scripts.py
myautoresizer.egg-info/PKG-INFO
myautoresizer.egg-info/SOURCES.txt
myautoresizer.egg-info/dependency_links.txt
myautoresizer.egg-info/entry_points.txt
myautoresizer.egg-info/top_level.txt