Metadata-Version: 1.0
Name: myautoresizer
Version: 0.1.6
Summary: Automatically resize and move GDK windows according to the configuration file
Home-page: https://github.com/seinohitomi/my-autoresizer
Author: Alex Wong
Author-email: alex@gmem.cc
License: UNKNOWN
Platform: UNKNOWN
